lask-0.2.0.dist-info/licenses/LICENSE
src/__init__.py
src/config.py
src/main.py
src/providers/__init__.py
src/providers/anthropic.py
src/providers/aws.py
src/providers/azure.py
src/providers/openai.py
lask-0.2.0.dist-info/METADATA
lask-0.2.0.dist-info/WHEEL
lask-0.2.0.dist-info/entry_points.txt
lask-0.2.0.dist-info/top_level.txt
lask-0.2.0.dist-info/RECORD
