Metadata-Version: 2.4
Name: lask
Version: 0.2.0
Summary: Ask your llm from the command line
Author: Open Source Lodge
License: GNU General Public License v3 (GPLv3)
Project-URL: Homepage, https://github.com/Open-Source-Lodge/lask
Project-URL: Repository, https://github.com/Open-Source-Lodge/lask
Project-URL: Documentation, https://github.com/Open-Source-Lodge/lask
Project-URL: Issue, https://github.com/Open-Source-Lodge/lask/issues
Project-URL: Changelog, https://github.com/Open-Source-Lodge/lask/releases
Classifier: Programming Language :: Python :: 3
Classifier: Operating System :: OS Independent
Requires-Python: >=3.9
License-File: LICENSE
Requires-Dist: requests>=2.32.3
Requires-Dist: setuptools>=80.8.0
Provides-Extra: aws
Requires-Dist: boto3>=1.28.0; extra == "aws"
Provides-Extra: all
Requires-Dist: boto3>=1.28.0; extra == "all"
Dynamic: license-file
